getit/__init__.py
getit/__main__.py
getit/cli.py
getit/config.py
getit/core/__init__.py
getit/core/downloader.py
getit/core/manager.py
getit/extractors/__init__.py
getit/extractors/base.py
getit/extractors/gofile.py
getit/extractors/mediafire.py
getit/extractors/mega.py
getit/extractors/onefichier.py
getit/extractors/pixeldrain.py
getit/storage/__init__.py
getit/storage/history.py
getit/tui/__init__.py
getit/tui/app.py
getit/tui/screens/__init__.py
getit/tui/screens/add_url.py
getit/tui/widgets/status_bar.py
getit/utils/__init__.py
getit/utils/http.py
getit/utils/logging.py
getit/utils/pacer.py
getit/utils/sanitize.py
getit_cli-0.2.0.dist-info/METADATA
getit_cli-0.2.0.dist-info/WHEEL
getit_cli-0.2.0.dist-info/entry_points.txt
getit_cli-0.2.0.dist-info/licenses/LICENSE
getit_cli-0.2.0.dist-info/RECORD
