Metadata-Version: 2.4
Name: getit-cli
Version: 0.2.0
Summary: Universal file hosting downloader with TUI - supports GoFile, PixelDrain, MediaFire, 1Fichier, Mega.nz
Project-URL: Homepage, https://github.com/Eltigani-web/getit
Project-URL: Repository, https://github.com/Eltigani-web/getit
Project-URL: Issues, https://github.com/Eltigani-web/getit/issues
Author: getit contributors
License-Expression: GPL-3.0-or-later
License-File: LICENSE
Keywords: 1fichier,async,cli,download,file-hosting,gofile,mediafire,mega,pixeldrain,tui
Classifier: Development Status :: 4 - Beta
Classifier: Environment :: Console
Classifier: Intended Audience :: End Users/Desktop
Classifier: License :: OSI Approved :: GNU General Public License v3 (GPLv3)
Classifier: Operating System :: OS Independent
Classifier: Programming Language :: Python :: 3
Classifier: Programming Language :: Python :: 3.11
Classifier: Programming Language :: Python :: 3.12
Classifier: Programming Language :: Python :: 3.13
Classifier: Topic :: Internet :: WWW/HTTP
Classifier: Topic :: Utilities
Requires-Python: >=3.11
Requires-Dist: aiofiles>=24.1.0
Requires-Dist: aiohttp>=3.9.0
Requires-Dist: aiolimiter>=1.1.0
Requires-Dist: aiosqlite>=0.20.0
Requires-Dist: beautifulsoup4>=4.12.0
Requires-Dist: httpx>=0.27.0
Requires-Dist: lxml>=5.2.0
Requires-Dist: pycryptodomex>=3.20.0
Requires-Dist: pydantic-settings>=2.3.0
Requires-Dist: pydantic>=2.7.0
Requires-Dist: pyyaml>=6.0.0
Requires-Dist: rich>=13.7.0
Requires-Dist: tenacity>=8.3.0
Requires-Dist: textual>=0.70.0
Requires-Dist: typer>=0.12.0
Provides-Extra: dev
Requires-Dist: mypy>=1.10.0; extra == 'dev'
Requires-Dist: pytest-asyncio>=0.23.0; extra == 'dev'
Requires-Dist: pytest-cov>=5.0.0; extra == 'dev'
Requires-Dist: pytest>=8.2.0; extra == 'dev'
Requires-Dist: ruff>=0.4.0; extra == 'dev'
Requires-Dist: types-aiofiles>=24.1.0; extra == 'dev'
